Workbook

Sheet Zakázky
A1: Info od | B1: Stav | C1: Deadline | E1: Akce | F1: Klient | G1: Bílá vana | H1: Schod | I1: Iso | J1: Prost | K1: Vylam | L1: Smyk | M1: Vibr | N1: poznámka | O1: Voplakal
A3: 46255 | B3: jiný | D3: Milan Soukup | E3: Česká mincovna Jablonec | F3: VALME s.r.o. | N3: dořešit nabídku Gmyse
A4: 46255 | B4: jiný | D4: Jiří Cír | E4: Ekorezidence Smíchov | F4: PP 53, a.s. | I4: x | N4: dořešit s Dubeckým
A5: 46255 | B5: jiný | D5: Jiří Cír | E5: BD Košinka | F5: PP 53, a.s.
A6: 46254 | B6: jiný | D6: Milan Soukup | E6: Milan | F6: VALENS, s.r.o.
A7: 46254 | B7: jiný | D7: Milan Soukup | E7: BD Boettingerova | F7: MAVI monolity s.r.o. | N7: poslat certifikáty, technické listy apod
A8: 46254 | B8: zpracováno | D8: Milan Soukup | E8: BD Labuťka | F8: V-STAV A, spol. s r.o.
A9: 46253 | B9: zpracováno | D9: Milan Soukup | E9: Branišovská | F9: V.D.O. Group s.r.o. | N9: cena dsl42
A10: 46253 | B10: jiný | D10: Jiří Cír | E10: BD Šumavská | F10: BETOKON s.r.o.
A11: 46253 | B11: zpracováno | D11: Milan Soukup | E11: RD Kolovraty | F11: PROFI - TESAŘI s.r.o.
A12: 46252 | B12: jiný | C12: 46255 | D12: Milan Soukup | E12: Mukařov | F12: ARDEM STAVEBNÍ s.r.o.
A13: 46251 | B13: jiný | D13: Jan Mayer | E13: Park Living Holešovice | F13: PORR a.s.
A14: 46251 | B14: zpracováno | C14: 46253 | D14: Milan Soukup | E14: Ladronka Park | F14: ARDEM STAVEBNÍ s.r.o.
A15: 46251 | B15: jiný | D15: Milan Soukup | E15: Škola Da Vinci | F15: Live Dream Create s.r.o.
A16: 46251 | B16: zpracováno | D16: Jan Mayer | E16: BD Hartigova | F16: PORR a.s. | I16: x
A17: 46251 | B17: zpracováno | D17: Jiří Cír | E17: Křeslická | F17: PRAGIS a.s. | N17: lift boxy
A18: 46248 | B18: zpracováno | D18: Jiří Cír | E18: BD Odkolek | F18: Metrostav a.s. | N18: GR desky
A19: 46247 | B19: jiný | C19: 46248 | D19: Milan Soukup | E19: Rezidence Balabenka | F19: ARDEM STAVEBNÍ s.r.o. | M19: x
A20: 46247 | B20: zpracováno | D20: Jan Mayer | E20: Senovážné náměstí | F20: BBP monolit s.r.o. | I20: x
A21: 46247 | B21: zpracováno | C21: 46251 | D21: Milan Soukup | E21: ZŠ Vodňanského | F21: ARDEM STAVEBNÍ s.r.o.
A22: 46247 | B22: zpracováno | D22: Milan Soukup | E22: Vinohradská | F22: STRABAG a.s. | H22: x
A23: 46247 | B23: jiný | D23: Milan Soukup | E23: PPO Karlín | F23: SMP Vodohospodářské stavby a.s. | N23: dilatační pás - zjistit od Milana, s kým řešil v SICE
A24: 46246 | B24: zpracováno | D24: Milan Soukup | E24: BD Prodloužená | F24: PROFI - TESAŘI s.r.o.
A25: 46246 | B25: zpracováno | D25: Milan Soukup | E25: Hotel Hladina | F25: REKAWI s.r.o. | L25: x
A26: 46246 | B26: zpracováno | D26: Milan Soukup | E26: Kladno BD A6 | F26: SLÁDEK GROUP, a.s.
A27: 46245 | B27: zpracováno | D27: Milan Soukup | E27: Milan | F27: Stavební firma HOBST a.s. | N27: přepravní úchyty
A28: 46244 | B28: zpracováno | D28: Jiří Cír | E28: Galerie Pardubice | F28: SYNER, s.r.o. | K28: x
A29: 46241 | B29: zpracováno | D29: Milan Soukup | E29: BD Nový Zeleneč | F29: ARDEM STAVEBNÍ s.r.o.
A30: 46241 | B30: zpracováno | D30: Milan Soukup | E30: Milan | F30: MAVI monolity s.r.o. | N30: tmely
A31: 46240 | B31: zpracováno | D31: Milan Soukup | E31: MERCEDES - BENZ TRUCKS | F31: HRABÁNEK s.r.o. | N31: kluzné trny
A32: 46239 | B32: zpracováno | D32: Jiří Cír | E32: Hydropolis | F32: PRAGIS a.s.
A33: 46239 | B33: zpracováno | D33: Milan Soukup | E33: UP Pardubice | F33: PEVE Construct s.r.o. | N33: čekáme na aktualizaci smykovky
A34: 46239 | B34: zpracováno | D34: Jan Mayer | E34: Čimice | F34: PORR a.s.
A35: 46238 | B35: zpracováno | D35: Milan Soukup | E35: CN Rezidence Balabenka | F35: ARDEM STAVEBNÍ s.r.o.
A36: 46238 | B36: zpracováno | D36: Milan Soukup | E36: Sweetwater | F36: SWIETELSKY stavební s.r.o. | L36: x
A37: 46233 | B37: zpracováno | C37: 46234 | D37: Milan Soukup | E37: P+R DEPO Hostivař | F37: STRABAG a.s.
A38: 46232 | B38: zpracováno | D38: Milan Soukup | E38: BD Březinova | F38: Gardenline s.r.o. | I38: x | L38: x
A39: 46232 | B39: jiný | D39: Milan Soukup | E39: Sociální bydlení Na Žižkově, Liberec | F39: VALME s.r.o.
A40: 46232 | B40: zrušeno | D40: Milan Soukup | E40: Vinohradská | F40: STRABAG a.s. | J40: x | N40: přidat pažnici 400/350
A41: 46231 | B41: zpracováno | D41: Milan Soukup | E41: BD Kročehlavy | F41: SLÁDEK GROUP, a.s. | L41: x
A42: 46231 | B42: zrušeno | D42: Milan Soukup | E42: Rezidence Koruna | F42: S T A K O společnost s ručením omezeným | I42: x | N42: dořeší Honza
A43: 46230 | B43: zpracováno | D43: Milan Soukup | E43: Rezidence Lipno přístav | F43: HLAVA - STAVBY s.r.o.
A44: 46227 | B44: připraveno | D44: Milan Soukup | E44: Hangár letiště Čáslav | F44: dpcon s.r.o.
A45: 46227 | B45: zpracováno | D45: Milan Soukup | E45: RD Chrastava | F45: Skramuský Radek | I45: x
A46: 46226 | B46: zpracováno | D46: Jiří Cír | E46: Ostravice "pila" | F46: JS Monolity, s.r.o.
A47: 46226 | B47: zpracováno | D47: Milan Soukup | E47: BD Plzeň | F47: BAUFERA s.r.o.
A48: 46226 | B48: zpracováno | D48: Milan Soukup | E48: Milan | F48: Live Dream Create s.r.o. | J48: x | N48: viz mail 23/7
A49: 46226 | B49: zrušeno | D49: Milan Soukup | E49: Milan | F49: Winning PS - Pamstav s.r.o. | N49: Kunex, viz mail 23/7 - vyřeší si Milan
A50: 46224 | B50: zpracováno | C50: 46227 | D50: Milan Soukup | E50: Nemocnice Mladá Boleslav | F50: ARDEM STAVEBNÍ s.r.o.
A51: 46224 | B51: zpracováno | C51: 46233 | D51: Milan Soukup | E51: Pavilon pro matku a dítě | F51: STRABAG a.s. | N51: dtto ARDEM
A52: 46224 | B52: zpracováno | D52: Milan Soukup | E52: BD Ruprechtická | F52: VALME s.r.o. | M52: x
A53: 46224 | B53: zpracováno | D53: Jiří Cír | E53: Beroun Pískovna II | F53: STEP, spol.s r.o.
A54: 46224 | B54: zpracováno | D54: Milan Soukup | E54: BD Rezidence Máchovo jezero | F54: VALME s.r.o.
A55: 46224 | B55: zpracováno | C55: 46230 | D55: Milan Soukup | E55: Nová Waltrovka obj. G1-G7 | F55: STRABAG a.s. | N55: vypadá to na vibrošku
A56: 46223 | B56: zpracováno | D56: Jiří Cír | E56: BD Mlazická | F56: PP 53, a.s. | N56: čekáme na izo
A57: 46223 | B57: zpracováno | C57: 46230 | D57: Jan Mayer | E57: Nová Waltrovka obj. G1-G7 | F57: PORR a.s. | N57: vypadá to na vibrošku
A58: 46223 | B58: zpracováno | D58: Milan Soukup | E58: Jistebník | F58: BAUFERA s.r.o. | I58: x
A59: 46223 | B59: zpracováno | D59: Milan Soukup | E59: Horní stanice Hromovka 2 | F59: BETONSERVIS s.r.o. | K59: x
A60: 46223 | B60: zpracováno | D60: Milan Soukup | E60: Campus Česká Spořitelna | F60: STRABAG a.s. | K60: x | L60: x
A61: 46223 | B61: zpracováno | D61: Jan Mayer | E61: Hůry | F61: PREFA Roudná s. r. o.
A62: 46220 | B62: zpracováno | D62: Jiří Cír | E62: BD Na Primoně | F62: MONOKON s.r.o. | I62: x | N62: zadat PEIKKO
A63: 46220 | B63: zpracováno | C63: 46230 | D63: Jiří Cír | E63: Rohan City Block B2 | F63: FERI, s.r.o.
A64: 46220 | B64: zpracováno | D64: Milan Soukup | E64: BD Sabinova Brno | F64: VALENS, s.r.o. | H64: x
A65: 46220 | B65: zpracováno | D65: Milan Soukup | E65: Milan | F65: BAUFERA s.r.o. | L65: x
A66: 46219 | B66: zpracováno | D66: Milan Soukup | E66: OS Kunratice u Liberece | F66: SYNER, s.r.o. | K66: x
A67: 46219 | B67: zpracováno | D67: Milan Soukup | E67: AH Votice | F67: ARDEM STAVEBNÍ s.r.o.
A68: 46219 | B68: zpracováno | D68: Milan Soukup | E68: Škola Da Vinci | F68: Live Dream Create s.r.o. | J68: x
A69: 46219 | B69: zpracováno | D69: Milan Soukup | E69: AD Otakarova | F69: VALENS, s.r.o.
A70: 46218 | B70: zpracováno | D70: Jan Mayer | E70: Dělnický dům PEKLO | F70: D - beton s.r.o. | I70: x | J70: x
A71: 46218 | B71: zpracováno | D71: Jiří Cír | E71: BD Tovačovského | F71: BK25, s.r.o.
A72: 46217 | B72: zpracováno | D72: Milan Soukup | E72: PPO Karlín | F72: SMP Vodohospodářské stavby a.s.
A73: 46217 | B73: jiný | D73: Jiří Cír | E73: Medový újezd | F73: Drechsler | I73: x | N73: volat v pondělí 20/7
A74: 46217 | B74: zpracováno | D74: Jiří Cír | E74: Galerie Pardubice | F74: SYNER, s.r.o. | I74: x | N74: čekáme na izo
A75: 46217 | B75: zpracováno | D75: Jiří Cír | E75: BD Parmská | F75: PP 53, a.s.
A76: 46217 | B76: zpracováno | D76: Jiří Cír | E76: RD Zbuzany | F76: Flash Partners s.r.o. | I76: x
A77: 46217 | B77: zpracováno | D77: Milan Soukup | E77: Milan | F77: BAUFERA s.r.o. | L77: x
A78: 46216 | B78: zpracováno | D78: Jiří Cír | E78: PD Mukařov | F78: Arch Construct s.r.o.
A79: 46214 | B79: zpracováno | D79: Milan Soukup | E79: Papírna N1 | F79: MAVI monolity s.r.o. | I79: x | N79: udělat kladečák 6.NP-14.NP
A80: 46213 | B80: zpracováno | D80: Milan Soukup | E80: Nedvězí u Olomouce | F80: VALENS, s.r.o. | I80: x
A81: 46212 | B81: zpracováno | D81: Jiří Cír | E81: BD Na Primoně | F81: MONOKON s.r.o.
A82: 46212 | B82: zpracováno | D82: Milan Soukup | E82: Branišovská | F82: V.D.O. Group s.r.o. | L82: x
A83: 46211 | B83: zpracováno | C83: 46216 | D83: Jan Mayer | E83: Bydlení META Modřany | F83: PORR a.s.
A84: 46210 | B84: zpracováno | C84: 46213 | D84: Milan Soukup | E84: Bydlení META Modřany | F84: STRABAG a.s.
A85: 46210 | B85: zpracováno | C85: 46220 | D85: Milan Soukup | E85: PSA Řeporyje (Mercedes) | F85: STRABAG a.s.
A86: 46210 | B86: zpracováno | D86: Jan Mayer | E86: Nová Linecká čtvrť - České Budějovice | F86: Metrostav a.s.
A87: 46210 | B87: zpracováno | D87: Milan Soukup | E87: Vinohradská | F87: STRABAG a.s. | K87: x
A88: 46206 | B88: jiný | C88: 46216 | D88: Milan Soukup | E88: Palác Hybernia | F88: STRABAG a.s. | N88: přeposílalo MAVI
A89: 46209 | B89: zpracováno | D89: Milan Soukup | E89: Vinohradská | F89: STRABAG a.s. | L89: x
A90: 46206 | B90: zpracováno | D90: Jiří Cír | E90: Jirka | F90: BAUFERA s.r.o. | N90: dořešit kosti!
A91: 46206 | B91: zpracováno | D91: Jiří Cír | E91: Křeslická | F91: PRAGIS a.s. | M91: x
A92: 46205 | B92: zpracováno | D92: Jiří Cír | E92: Chata Krásná | F92: JS Monolity, s.r.o. | I92: x
A93: 46205 | B93: zpracováno | D93: Jiří Cír | E93: Na Homoli | F93: FERI, s.r.o. | I93: x | N93: 3 podlaží najednou, kolik palet? 3. srpen dál
A94: 46205 | B94: zpracováno | D94: Jan Mayer | E94: BD Plzeň | F94: Stavební společnost SIPA s.r.o. | I94: x | N94: doplnit do nabídky
A95: 46205 | B95: zpracováno | D95: Jan Mayer | E95: Trafostanice Skvrňany | F95: MIVO | G95: x
A96: 46205 | B96: zpracováno | D96: Jan Mayer | E96: BD Zahrádky Branišovská | F96: BADITECH s.r.o. | G96: x | N96: Honza si udělal sám
A97: 46204 | B97: zpracováno | D97: Jiří Cír | E97: Jirka | F97: PP 53, a.s. | N97: dilatace opěrka
A98: 46204 | B98: zpracováno | D98: Jan Mayer | E98: BD Křimice | F98: BBP monolit s.r.o. | I98: x | N98: vlastní návrh
A99: 46203 | B99: zpracováno | D99: Milan Soukup | E99: CN Office Park | F99: ARDEM STAVEBNÍ s.r.o.
A100: 46203 | B100: zpracováno | D100: Milan Soukup | E100: City Blok Kleinerova | F100: ARDEM STAVEBNÍ s.r.o. | M100: x | N100: sylomer viz PP53 - Billa Kladno
A101: 46202 | B101: zpracováno | D101: Milan Soukup | E101: Modernizace Nemocnice Frýdlant | F101: VALME s.r.o. | L101: x
...

Sheet Poptávky
A1: Dodavatel | B1: Poptáno | C1: Obdrženo | D1: Klient | E1: Akce | F1: Uvedená akce | G1: Poptáváno | H1: poznámka | I1: Předmět mailu
I2: ="Poptávka TURTO - "&A2&" - "&IF(F2=data!$E$2,"",E2&" - ")&G2&" - "&DAY(B2)&"."&MONTH(B2)&"."&YEAR(B2) -> Poptávka TURTO - - - - 0.1.1900
A3: Leviat | B3: 46255 | D3: PP 53, a.s. | E3: BD Košinka | F3: ano | G3: izolační nosníky | I3: ="Poptávka TURTO - "&A3&" - "&IF(F3=data!$E$1,E3&" - ","")&G3&" - "&DAY(B3)&"."&MONTH(B3)&"."&YEAR(B3) -> Poptávka TURTO - Leviat - BD Košinka - izolační nosníky - 21.8.2026
A4: Leviat | B4: 46255 | D4: PORR a.s. | E4: Park Living Holešovice | F4: ano | G4: izolační nosníky | I4: ="Poptávka TURTO - "&A4&" - "&IF(F4=data!$E$1,E4&" - ","")&G4&" - "&DAY(B4)&"."&MONTH(B4)&"."&YEAR(B4) -> Poptávka TURTO - Leviat - Park Living Holešovice - izolační nosníky - 21.8.2026
A5: GeroTop | B5: 46255 | C5: 46255 | D5: HSF System a.s. | E5: Milan | F5: ne | G5: prostupy | I5: ="Poptávka TURTO - "&A5&" - "&IF(F5=data!$E$1,E5&" - ","")&G5&" - "&DAY(B5)&"."&MONTH(B5)&"."&YEAR(B5) -> Poptávka TURTO - GeroTop - prostupy - 21.8.2026
A6: Peikko | B6: 46255 | D6: PP 53, a.s. | E6: Ekorezidence Smíchov | F6: ano | G6: izolační nosníky | I6: ="Poptávka TURTO - "&A6&" - "&IF(F6=data!$E$1,E6&" - ","")&G6&" - "&DAY(B6)&"."&MONTH(B6)&"."&YEAR(B6) -> Poptávka TURTO - Peikko - Ekorezidence Smíchov - izolační nosníky - 21.8.2026
A7: Leviat | B7: 46255 | C7: 46255 | D7: MAVI monolity s.r.o. | E7: Papírna N1 | F7: ano | G7: izolační nosníky | I7: ="Poptávka TURTO - "&A7&" - "&IF(F7=data!$E$1,E7&" - ","")&G7&" - "&DAY(B7)&"."&MONTH(B7)&"."&YEAR(B7) -> Poptávka TURTO - Leviat - Papírna N1 - izolační nosníky - 21.8.2026
A8: GeroTop | B8: 46254 | C8: 46254 | D8: SWIETELSKY stavební s.r.o. | E8: Milan | F8: ne | G8: prostupy | I8: ="Poptávka TURTO - "&A8&" - "&IF(F8=data!$E$1,E8&" - ","")&G8&" - "&DAY(B8)&"."&MONTH(B8)&"."&YEAR(B8) -> Poptávka TURTO - GeroTop - prostupy - 20.8.2026
A9: Nevoga | B9: 46254 | D9: SDMstav Praha s.r.o | E9: BD Zenklova | F9: ne | G9: vylamovací výztuž | I9: ="Poptávka TURTO - "&A9&" - "&IF(F9=data!$E$1,E9&" - ","")&G9&" - "&DAY(B9)&"."&MONTH(B9)&"."&YEAR(B9) -> Poptávka TURTO - Nevoga - vylamovací výztuž - 20.8.2026
A10: GeroTop | B10: 46253 | C10: 46254 | D10: PROFI - TESAŘI s.r.o. | E10: RD Kolovraty | F10: ne | G10: prostupy | I10: ="Poptávka TURTO - "&A10&" - "&IF(F10=data!$E$1,E10&" - ","")&G10&" - "&DAY(B10)&"."&MONTH(B10)&"."&YEAR(B10) -> Poptávka TURTO - GeroTop - prostupy - 19.8.2026
A11: Peikko | B11: 46253 | C11: 46255 | D11: BETOKON s.r.o. | E11: BD Šumavská | F11: ano | G11: smyková výztuž | I11: ="Poptávka TURTO - "&A11&" - "&IF(F11=data!$E$1,E11&" - ","")&G11&" - "&DAY(B11)&"."&MONTH(B11)&"."&YEAR(B11) -> Poptávka TURTO - Peikko - BD Šumavská - smyková výztuž - 19.8.2026
A12: PohlCon | B12: 46253 | C12: 46253 | D12: BETOKON s.r.o. | E12: BD Šumavská | F12: ne | G12: smyková výztuž | I12: ="Poptávka TURTO - "&A12&" - "&IF(F12=data!$E$1,E12&" - ","")&G12&" - "&DAY(B12)&"."&MONTH(B12)&"."&YEAR(B12) -> Poptávka TURTO - PohlCon - smyková výztuž - 19.8.2026
A13: Leviat | B13: 46253 | D13: BETOKON s.r.o. | E13: BD Šumavská | F13: ano | G13: smyková výztuž | I13: ="Poptávka TURTO - "&A13&" - "&IF(F13=data!$E$1,E13&" - ","")&G13&" - "&DAY(B13)&"."&MONTH(B13)&"."&YEAR(B13) -> Poptávka TURTO - Leviat - BD Šumavská - smyková výztuž - 19.8.2026
A14: GeroTop | B14: 46253 | C14: 46253 | D14: V.D.O. Group s.r.o. | E14: Milan | F14: ne | G14: prostupy | I14: ="Poptávka TURTO - "&A14&" - "&IF(F14=data!$E$1,E14&" - ","")&G14&" - "&DAY(B14)&"."&MONTH(B14)&"."&YEAR(B14) -> Poptávka TURTO - GeroTop - prostupy - 19.8.2026
A15: GeroTop | B15: 46252 | C15: 46252 | D15: AKTIVITA plus s.r.o. | F15: ne | G15: prostupy | I15: ="Poptávka TURTO - "&A15&" - "&IF(F15=data!$E$1,E15&" - ","")&G15&" - "&DAY(B15)&"."&MONTH(B15)&"."&YEAR(B15) -> Poptávka TURTO - GeroTop - prostupy - 18.8.2026
A16: JFP TRADE | B16: 46251 | C16: 46253 | D16: ARDEM STAVEBNÍ s.r.o. | E16: Ladronka Park | F16: ano | G16: Sylomer | I16: ="Poptávka TURTO - "&A16&" - "&IF(F16=data!$E$1,E16&" - ","")&G16&" - "&DAY(B16)&"."&MONTH(B16)&"."&YEAR(B16) -> Poptávka TURTO - JFP TRADE - Ladronka Park - Sylomer - 17.8.2026
A17: PohlCon | B17: 46251 | C17: 46252 | D17: ARDEM STAVEBNÍ s.r.o. | E17: Ladronka Park | F17: ne | G17: smyková výztuž | I17: ="Poptávka TURTO - "&A17&" - "&IF(F17=data!$E$1,E17&" - ","")&G17&" - "&DAY(B17)&"."&MONTH(B17)&"."&YEAR(B17) -> Poptávka TURTO - PohlCon - smyková výztuž - 17.8.2026
A18: Leviat | B18: 46251 | C18: 46253 | D18: ARDEM STAVEBNÍ s.r.o. | E18: Ladronka Park | F18: ano | G18: izolační nosníky | I18: ="Poptávka TURTO - "&A18&" - "&IF(F18=data!$E$1,E18&" - ","")&G18&" - "&DAY(B18)&"."&MONTH(B18)&"."&YEAR(B18) -> Poptávka TURTO - Leviat - Ladronka Park - izolační nosníky - 17.8.2026
A19: Leviat | B19: 46251 | C19: 46251 | D19: PORR a.s. | E19: BD Hartigova | F19: ano | G19: izolační nosníky | I19: ="Poptávka TURTO - "&A19&" - "&IF(F19=data!$E$1,E19&" - ","")&G19&" - "&DAY(B19)&"."&MONTH(B19)&"."&YEAR(B19) -> Poptávka TURTO - Leviat - BD Hartigova - izolační nosníky - 17.8.2026
A20: Leviat | B20: 46251 | C20: 46251 | D20: PRAGIS a.s. | E20: Křeslická | F20: ne | G20: Lift-box | I20: ="Poptávka TURTO - "&A20&" - "&IF(F20=data!$E$1,E20&" - ","")&G20&" - "&DAY(B20)&"."&MONTH(B20)&"."&YEAR(B20) -> Poptávka TURTO - Leviat - Lift-box - 17.8.2026
A21: Leviat | B21: 46248 | C21: 46248 | D21: ARDEM STAVEBNÍ s.r.o. | E21: ZŠ Vodňanského | F21: ne | G21: akustika | I21: ="Poptávka TURTO - "&A21&" - "&IF(F21=data!$E$1,E21&" - ","")&G21&" - "&DAY(B21)&"."&MONTH(B21)&"."&YEAR(B21) -> Poptávka TURTO - Leviat - akustika - 14.8.2026
A22: Leviat | B22: 46248 | C22: 46252 | D22: ARDEM STAVEBNÍ s.r.o. | E22: ZŠ Vodňanského | F22: ano | G22: izolační nosníky | I22: ="Poptávka TURTO - "&A22&" - "&IF(F22=data!$E$1,E22&" - ","")&G22&" - "&DAY(B22)&"."&MONTH(B22)&"."&YEAR(B22) -> Poptávka TURTO - Leviat - ZŠ Vodňanského - izolační nosníky - 14.8.2026
A23: Pragoelast | B23: 46248 | C23: 46248 | D23: Metrostav a.s. | E23: BD Odkolek | F23: ne | G23: GR desky | I23: ="Poptávka TURTO - "&A23&" - "&IF(F23=data!$E$1,E23&" - ","")&G23&" - "&DAY(B23)&"."&MONTH(B23)&"."&YEAR(B23) -> Poptávka TURTO - Pragoelast - GR desky - 14.8.2026
A24: JFP TRADE | B24: 46247 | C24: 46248 | D24: ARDEM STAVEBNÍ s.r.o. | E24: Rezidence Balabenka | F24: ne | G24: Sylomer | I24: ="Poptávka TURTO - "&A24&" - "&IF(F24=data!$E$1,E24&" - ","")&G24&" - "&DAY(B24)&"."&MONTH(B24)&"."&YEAR(B24) -> Poptávka TURTO - JFP TRADE - Sylomer - 13.8.2026
A25: Leviat | B25: 46247 | C25: 46248 | D25: BBP monolit s.r.o. | E25: Senovážné náměstí | F25: ano | G25: izolační nosníky | I25: ="Poptávka TURTO - "&A25&" - "&IF(F25=data!$E$1,E25&" - ","")&G25&" - "&DAY(B25)&"."&MONTH(B25)&"."&YEAR(B25) -> Poptávka TURTO - Leviat - Senovážné náměstí - izolační nosníky - 13.8.2026
A26: SIKA | B26: 46247 | D26: SMP Vodohospodářské stavby a.s. | E26: PPO Karlín | F26: ne | G26: PVC pásy | I26: ="Poptávka TURTO - "&A26&" - "&IF(F26=data!$E$1,E26&" - ","")&G26&" - "&DAY(B26)&"."&MONTH(B26)&"."&YEAR(B26) -> Poptávka TURTO - SIKA - PVC pásy - 13.8.2026
A27: Peikko | B27: 46246 | D27: REKAWI s.r.o. | E27: Hotel Hladina | F27: ano | G27: smyková výztuž | I27: ="Poptávka TURTO - "&A27&" - "&IF(F27=data!$E$1,E27&" - ","")&G27&" - "&DAY(B27)&"."&MONTH(B27)&"."&YEAR(B27) -> Poptávka TURTO - Peikko - Hotel Hladina - smyková výztuž - 12.8.2026
A28: PohlCon | B28: 46246 | C28: 46246 | D28: REKAWI s.r.o. | E28: Hotel Hladina | F28: ne | G28: smyková výztuž | I28: ="Poptávka TURTO - "&A28&" - "&IF(F28=data!$E$1,E28&" - ","")&G28&" - "&DAY(B28)&"."&MONTH(B28)&"."&YEAR(B28) -> Poptávka TURTO - PohlCon - smyková výztuž - 12.8.2026
A29: GeroTop | B29: 46246 | C29: 46246 | D29: SLÁDEK GROUP, a.s. | E29: Kladno BD A6 | F29: ne | G29: prostupy | I29: ="Poptávka TURTO - "&A29&" - "&IF(F29=data!$E$1,E29&" - ","")&G29&" - "&DAY(B29)&"."&MONTH(B29)&"."&YEAR(B29) -> Poptávka TURTO - GeroTop - prostupy - 12.8.2026
A30: GMYS | B30: 46246 | C30: 46254 | D30: VALME s.r.o. | E30: Česká mincovna Jablonec | F30: ne | G30: izolační nosníky | I30: ="Poptávka TURTO - "&A30&" - "&IF(F30=data!$E$1,E30&" - ","")&G30&" - "&DAY(B30)&"."&MONTH(B30)&"."&YEAR(B30) -> Poptávka TURTO - GMYS - izolační nosníky - 12.8.2026
A31: Peikko | B31: 46245 | D31: Stavební firma HOBST a.s. | E31: Milan | F31: ne | G31: přepravní kotvy | I31: ="Poptávka TURTO - "&A31&" - "&IF(F31=data!$E$1,E31&" - ","")&G31&" - "&DAY(B31)&"."&MONTH(B31)&"."&YEAR(B31) -> Poptávka TURTO - Peikko - přepravní kotvy - 11.8.2026
A32: PohlCon | B32: 46245 | C32: 46246 | D32: Stavební firma HOBST a.s. | E32: Milan | F32: ne | G32: přepravní kotvy | I32: ="Poptávka TURTO - "&A32&" - "&IF(F32=data!$E$1,E32&" - ","")&G32&" - "&DAY(B32)&"."&MONTH(B32)&"."&YEAR(B32) -> Poptávka TURTO - PohlCon - přepravní kotvy - 11.8.2026
A33: Leviat | B33: 46245 | C33: 46246 | D33: Hinton, a.s. | E33: Za Valem D1,D2,D3, I | F33: ano | G33: izolační nosníky | I33: ="Poptávka TURTO - "&A33&" - "&IF(F33=data!$E$1,E33&" - ","")&G33&" - "&DAY(B33)&"."&MONTH(B33)&"."&YEAR(B33) -> Poptávka TURTO - Leviat - Za Valem D1,D2,D3, I - izolační nosníky - 11.8.2026
A34: Nevoga | B34: 46244 | C34: 46245 | D34: SYNER, s.r.o. | E34: Galerie Pardubice | F34: ne | G34: vylamovací výztuž | I34: ="Poptávka TURTO - "&A34&" - "&IF(F34=data!$E$1,E34&" - ","")&G34&" - "&DAY(B34)&"."&MONTH(B34)&"."&YEAR(B34) -> Poptávka TURTO - Nevoga - vylamovací výztuž - 10.8.2026
A35: Leviat | B35: 46244 | C35: 46244 | D35: ARDEM STAVEBNÍ s.r.o. | E35: BD Nový Zeleneč | F35: ano | G35: izolační nosníky | I35: ="Poptávka TURTO - "&A35&" - "&IF(F35=data!$E$1,E35&" - ","")&G35&" - "&DAY(B35)&"."&MONTH(B35)&"."&YEAR(B35) -> Poptávka TURTO - Leviat - BD Nový Zeleneč - izolační nosníky - 10.8.2026
A36: SIKA | B36: 46244 | C36: 46244 | D36: MAVI monolity s.r.o. | E36: Milan | F36: ne | G36: Sikaflex Construction+ | I36: ="Poptávka TURTO - "&A36&" - "&IF(F36=data!$E$1,E36&" - ","")&G36&" - "&DAY(B36)&"."&MONTH(B36)&"."&YEAR(B36) -> Poptávka TURTO - SIKA - Sikaflex Construction+ - 10.8.2026
A37: Pro-Doma | B37: 46239 | C37: 46239 | D37: PRAGIS a.s. | E37: Hydropolis | F37: ne | G37: lenton spojky | I37: ="Poptávka TURTO - "&A37&" - "&IF(F37=data!$E$1,E37&" - ","")&G37&" - "&DAY(B37)&"."&MONTH(B37)&"."&YEAR(B37) -> Poptávka TURTO - Pro-Doma - lenton spojky - 5.8.2026
A38: MaxFrank | B38: 46239 | C38: 46239 | D38: PORR a.s. | E38: Čimice | F38: ne | G38: akustika | I38: ="Poptávka TURTO - "&A38&" - "&IF(F38=data!$E$1,E38&" - ","")&G38&" - "&DAY(B38)&"."&MONTH(B38)&"."&YEAR(B38) -> Poptávka TURTO - MaxFrank - akustika - 5.8.2026
A39: Leviat | B39: 46239 | C39: 46239 | D39: PORR a.s. | E39: Čimice | F39: ano | G39: izolační nosníky | I39: ="Poptávka TURTO - "&A39&" - "&IF(F39=data!$E$1,E39&" - ","")&G39&" - "&DAY(B39)&"."&MONTH(B39)&"."&YEAR(B39) -> Poptávka TURTO - Leviat - Čimice - izolační nosníky - 5.8.2026
A40: Peikko | B40: 46238 | C40: 46240 | D40: SWIETELSKY stavební s.r.o. | E40: Sweetwater | F40: ano | G40: smyková výztuž | I40: ="Poptávka TURTO - "&A40&" - "&IF(F40=data!$E$1,E40&" - ","")&G40&" - "&DAY(B40)&"."&MONTH(B40)&"."&YEAR(B40) -> Poptávka TURTO - Peikko - Sweetwater - smyková výztuž - 4.8.2026
A41: PohlCon | B41: 46238 | C41: 46146 | D41: SWIETELSKY stavební s.r.o. | E41: Sweetwater | F41: ne | G41: smyková výztuž | I41: ="Poptávka TURTO - "&A41&" - "&IF(F41=data!$E$1,E41&" - ","")&G41&" - "&DAY(B41)&"."&MONTH(B41)&"."&YEAR(B41) -> Poptávka TURTO - PohlCon - smyková výztuž - 4.8.2026
A42: Peikko | B42: 46233 | C42: 46244 | D42: MONOKON s.r.o. | E42: BD Na Primoně | F42: ano | G42: izolační nosníky | I42: ="Poptávka TURTO - "&A42&" - "&IF(F42=data!$E$1,E42&" - ","")&G42&" - "&DAY(B42)&"."&MONTH(B42)&"."&YEAR(B42) -> Poptávka TURTO - Peikko - BD Na Primoně - izolační nosníky - 30.7.2026
A43: Leviat | B43: 46232 | C43: 46233 | D43: Gardenline s.r.o. | E43: BD Březinova | F43: ano | G43: izolační nosníky | I43: ="Poptávka TURTO - "&A43&" - "&IF(F43=data!$E$1,E43&" - ","")&G43&" - "&DAY(B43)&"."&MONTH(B43)&"."&YEAR(B43) -> Poptávka TURTO - Leviat - BD Březinova - izolační nosníky - 29.7.2026
... A62: Leviat | B62: 46227 | C62: 46231 | D62: JS Monolity, s.r.o. | E62: Ostravice "pila" | F62: ano | G62: izolační nosníky | I62: ="Poptávka TURTO - "&A62&" - "&IF(F62=data!$E$1,E62&" - ","")&G62&" - "&DAY(B62)&"."&MONTH(B62)&"."&YEAR(B62) -> Poptávka TURTO - Leviat - Ostravice "pila" - izolační nosníky - 24.7.2026
A63: Nevoga | B63: 46227 | C63: 46231 | D63: Polymet | E63: Jirka | F63: ne | G63: izolační nosníky | H63: rovnou objednat | I63: ="Poptávka TURTO - "&A63&" - "&IF(F63=data!$E$1,E63&" - ","")&G63&" - "&DAY(B63)&"."&MONTH(B63)&"."&YEAR(B63) -> Poptávka TURTO - Nevoga - izolační nosníky - 24.7.2026
A64: Leviat | B64: 46226 | C64: 46226 | D64: MIVO | E64: Honza | F64: ne | G64: izolační nosníky | I64: ="Poptávka TURTO - "&A64&" - "&IF(F64=data!$E$1,E64&" - ","")&G64&" - "&DAY(B64)&"."&MONTH(B64)&"."&YEAR(B64) -> Poptávka TURTO - Leviat - izolační nosníky - 23.7.2026
A65: GeroTop | B65: 46226 | C65: 46226 | D65: Live Dream Create s.r.o. | E65: Milan | F65: ne | G65: prostupy | I65: ="Poptávka TURTO - "&A65&" - "&IF(F65=data!$E$1,E65&" - ","")&G65&" - "&DAY(B65)&"."&MONTH(B65)&"."&YEAR(B65) -> Poptávka TURTO - GeroTop - prostupy - 23.7.2026
A66: Peikko | B66: 46226 | C66: 46227 | D66: STRABAG a.s. | E66: Pavilon pro matku a dítě | F66: ano | G66: smyková výztuž | I66: ="Poptávka TURTO - "&A66&" - "&IF(F66=data!$E$1,E66&" - ","")&G66&" - "&DAY(B66)&"."&MONTH(B66)&"."&YEAR(B66) -> Poptávka TURTO - Peikko - Pavilon pro matku a dítě - smyková výztuž - 23.7.2026
A67: PohlCon | B67: 46226 | C67: 46227 | D67: STRABAG a.s. | E67: Pavilon pro matku a dítě | F67: ne | G67: smyková výztuž | I67: ="Poptávka TURTO - "&A67&" - "&IF(F67=data!$E$1,E67&" - ","")&G67&" - "&DAY(B67)&"."&MONTH(B67)&"."&YEAR(B67) -> Poptávka TURTO - PohlCon - smyková výztuž - 23.7.2026
A68: Leviat | B68: 46226 | C68: 46226 | D68: STRABAG a.s. | E68: Pavilon pro matku a dítě | F68: ano | G68: izolační nosníky | I68: ="Poptávka TURTO - "&A68&" - "&IF(F68=data!$E$1,E68&" - ","")&G68&" - "&DAY(B68)&"."&MONTH(B68)&"."&YEAR(B68) -> Poptávka TURTO - Leviat - Pavilon pro matku a dítě - izolační nosníky - 23.7.2026
A69: SANAX | B69: 46226 | C69: 46226 | D69: S.I.G.T. s.r.o. | E69: Milan | F69: ne | G69: Carbo lamela | I69: ="Poptávka TURTO - "&A69&" - "&IF(F69=data!$E$1,E69&" - ","")&G69&" - "&DAY(B69)&"."&MONTH(B69)&"."&YEAR(B69) -> Poptávka TURTO - SANAX - Carbo lamela - 23.7.2026
A70: Nevoga | B70: 46225 | C70: 46227 | D70: ARSWIN s.r.o. | E70: ČOV Kbely | F70: ano | G70: vylamovací výztuž | I70: ="Poptávka TURTO - "&A70&" - "&IF(F70=data!$E$1,E70&" - ","")&G70&" - "&DAY(B70)&"."&MONTH(B70)&"."&YEAR(B70) -> Poptávka TURTO - Nevoga - ČOV Kbely - vylamovací výztuž - 22.7.2026
A71: Leviat | B71: 46225 | C71: 46226 | D71: FERI, s.r.o. | E71: Rohan City Block B2 | F71: ano | G71: izolační nosníky | I71: ="Poptávka TURTO - "&A71&" - "&IF(F71=data!$E$1,E71&" - ","")&G71&" - "&DAY(B71)&"."&MONTH(B71)&"."&YEAR(B71) -> Poptávka TURTO - Leviat - Rohan City Block B2 - izolační nosníky - 22.7.2026
A72: GeroTop | B72: 46225 | C72: 46225 | D72: V-STAV A, spol. s r.o. | E72: Milan | F72: ne | G72: prostupy | I72: ="Poptávka TURTO - "&A72&" - "&IF(F72=data!$E$1,E72&" - ","")&G72&" - "&DAY(B72)&"."&MONTH(B72)&"."&YEAR(B72) -> Poptávka TURTO - GeroTop - prostupy - 22.7.2026
A73: SIKA | B73: 46225 | C73: 46225 | D73: S.I.G.T. s.r.o. | E73: Milan | F73: ne | G73: Carbo lamela | I73: ="Poptávka TURTO - "&A73&" - "&IF(F73=data!$E$1,E73&" - ","")&G73&" - "&DAY(B73)&"."&MONTH(B73)&"."&YEAR(B73) -> Poptávka TURTO - SIKA - Carbo lamela - 22.7.2026
A74: GeroTop | B74: 46225 | C74: 46225 | D74: PP 53, a.s. | E74: BD Mlazická | F74: ano | G74: prostupy | I74: ="Poptávka TURTO - "&A74&" - "&IF(F74=data!$E$1,E74&" - ","")&G74&" - "&DAY(B74)&"."&MONTH(B74)&"."&YEAR(B74) -> Poptávka TURTO - GeroTop - BD Mlazická - prostupy - 22.7.2026
A75: Leviat | B75: 46225 | C75: 46227 | D75: PP 53, a.s. | E75: BD Mlazická | F75: ano | G75: izolační nosníky | I75: ="Poptávka TURTO - "&A75&" - "&IF(F75=data!$E$1,E75&" - ","")&G75&" - "&DAY(B75)&"."&MONTH(B75)&"."&YEAR(B75) -> Poptávka TURTO - Leviat - BD Mlazická - izolační nosníky - 22.7.2026
... A108: Leviat | B108: 46211 | C108: 46211 | D108: VALME s.r.o. | E108: Česká mincovna Jablonec | F108: ano | G108: izolační nosníky | I108: ="Poptávka TURTO - "&A108&" - "&IF(F108=data!$E$1,E108&" - ","")&G108&" - "&DAY(B108)&"."&MONTH(B108)&"."&YEAR(B108) -> Poptávka TURTO - Leviat - Česká mincovna Jablonec - izolační nosníky - 8.7.2026
A109: GeroTop | B109: 46211 | D109: STRABAG a.s. | E109: Palác Hybernia | F109: ano | G109: prostupy | I109: ="Poptávka TURTO - "&A109&" - "&IF(F109=data!$E$1,E109&" - ","")&G109&" - "&DAY(B109)&"."&MONTH(B109)&"."&YEAR(B109) -> Poptávka TURTO - GeroTop - Palác Hybernia - prostupy - 8.7.2026
A110: Peikko | B110: 46210 | C110: 46230 | D110: PORR a.s. | E110: OS Nad Čimickým Údolím | F110: ano | G110: izolační nosníky | I110: ="Poptávka TURTO - "&A110&" - "&IF(F110=data!$E$1,E110&" - ","")&G110&" - "&DAY(B110)&"."&MONTH(B110)&"."&YEAR(B110) -> Poptávka TURTO - Peikko - OS Nad Čimickým Údolím - izolační nosníky - 7.7.2026
A111: Leviat | B111: 46210 | C111: 46211 | D111: STRABAG a.s. | E111: Bydlení META Modřany | F111: ano | G111: izolační nosníky | I111: ="Poptávka TURTO - "&A111&" - "&IF(F111=data!$E$1,E111&" - ","")&G111&" - "&DAY(B111)&"."&MONTH(B111)&"."&YEAR(B111) -> Poptávka TURTO - Leviat - Bydlení META Modřany - izolační nosníky - 7.7.2026
A112: Leviat | B112: 46210 | C112: 46211 | D112: Metrostav a.s. | E112: Linecká čtvrť - České Budějovice | F112: ano | G112: smykové trny | I112: ="Poptávka TURTO - "&A112&" - "&IF(F112=data!$E$1,E112&" - ","")&G112&" - "&DAY(B112)&"."&MONTH(B112)&"."&YEAR(B112) -> Poptávka TURTO - Leviat - Linecká čtvrť - České Budějovice - smykové trny - 7.7.2026
A113: Peikko | B113: 46210 | C113: 46211 | D113: Metrostav a.s. | E113: Linecká čtvrť - České Budějovice | F113: ne | G113: smykové trny | H113: NEUMÍ | I113: ="Poptávka TURTO - "&A113&" - "&IF(F113=data!$E$1,E113&" - ","")&G113&" - "&DAY(B113)&"."&MONTH(B113)&"."&YEAR(B113) -> Poptávka TURTO - Peikko - smykové trny - 7.7.2026
A114: PohlCon | B114: 46210 | C114: 46211 | D114: Metrostav a.s. | E114: Linecká čtvrť - České Budějovice | F114: ne | G114: smykové trny | I114: ="Poptávka TURTO - "&A114&" - "&IF(F114=data!$E$1,E114&" - ","")&G114&" - "&DAY(B114)&"."&MONTH(B114)&"."&YEAR(B114) -> Poptávka TURTO - PohlCon - smykové trny - 7.7.2026
A115: Nevoga | B115: 46210 | C115: 46212 | D115: STRABAG a.s. | E115: Vinohradská | F115: ne | G115: vylamovací výztuž | I115: ="Poptávka TURTO - "&A115&" - "&IF(F115=data!$E$1,E115&" - ","")&G115&" - "&DAY(B115)&"."&MONTH(B115)&"."&YEAR(B115) -> Poptávka TURTO - Nevoga - vylamovací výztuž - 7.7.2026
A116: Peikko | B116: 46209 | C116: 46210 | D116: STRABAG a.s. | E116: Vinohradská | F116: ano | G116: smyková výztuž | I116: ="Poptávka TURTO - "&A116&" - "&IF(F116=data!$E$1,E116&" - ","")&G116&" - "&DAY(B116)&"."&MONTH(B116)&"."&YEAR(B116) -> Poptávka TURTO - Peikko - Vinohradská - smyková výztuž - 6.7.2026
A117: JFP TRADE | B117: 46206 | C117: 46206 | D117: PRAGIS a.s. | E117: Křeslická | F117: ne | G117: Sylomer | I117: ="Poptávka TURTO - "&A117&" - "&IF(F117=data!$E$1,E117&" - ","")&G117&" - "&DAY(B117)&"."&MONTH(B117)&"."&YEAR(B117) -> Poptávka TURTO - JFP TRADE - Sylomer - 3.7.2026
A118: calenberg | B118: 46206 | C118: 46206 | D118: PRAGIS a.s. | E118: Křeslická | F118: ano | G118: vibroizolace | I118: ="Poptávka TURTO - "&A118&" - "&IF(F118=data!$E$1,E118&" - ","")&G118&" - "&DAY(B118)&"."&MONTH(B118)&"."&YEAR(B118) -> Poptávka TURTO - calenberg - Křeslická - vibroizolace - 3.7.2026
A119: Leviat | B119: 46205 | C119: 46206 | D119: JS Monolity, s.r.o. | E119: Chata Krásná | F119: ano | G119: izolační nosníky | I119: ="Poptávka TURTO - "&A119&" - "&IF(F119=data!$E$1,E119&" - ","")&G119&" - "&DAY(B119)&"."&MONTH(B119)&"."&YEAR(B119) -> Poptávka TURTO - Leviat - Chata Krásná - izolační nosníky - 2.7.2026
A120: GeroTop | B120: 46205 | D120: MIVO | E120: Trafostanice Skvrňany | F120: ano | G120: prostupy | I120: ="Poptávka TURTO - "&A120&" - "&IF(F120=data!$E$1,E120&" - ","")&G120&" - "&DAY(B120)&"."&MONTH(B120)&"."&YEAR(B120) -> Poptávka TURTO - GeroTop - Trafostanice Skvrňany - prostupy - 2.7.2026
A121: Peikko | B121: 46204 | C121: 46211 | D121: BETONSERVIS s.r.o. | E121: Dolní stanice Hromovka 2 | F121: ano | G121: izolační nosníky | I121: ="Poptávka TURTO - "&A121&" - "&IF(F121=data!$E$1,E121&" - ","")&G121&" - "&DAY(B121)&"."&MONTH(B121)&"."&YEAR(B121) -> Poptávka TURTO - Peikko - Dolní stanice Hromovka 2 - izolační nosníky - 1.7.2026
A122: PohlCon | B122: 46204 | C122: 46204 | D122: BETONSERVIS s.r.o. | E122: Dolní stanice Hromovka 2 | F122: ne | G122: izolační nosníky | H122: neumí | I122: ="Poptávka TURTO - "&A122&" - "&IF(F122=data!$E$1,E122&" - ","")&G122&" - "&DAY(B122)&"."&MONTH(B122)&"."&YEAR(B122) -> Poptávka TURTO - PohlCon - izolační nosníky - 1.7.2026
A123: calenberg | B123: 46203 | C123: 46204 | D123: ARDEM STAVEBNÍ s.r.o. | E123: City Blok Kleinerova | F123: ano | G123: vibroizolace | I123: ="Poptávka TURTO - "&A123&" - "&IF(F123=data!$E$1,E123&" - ","")&G123&" - "&DAY(B123)&"."&MONTH(B123)&"."&YEAR(B123) -> Poptávka TURTO - calenberg - City Blok Kleinerova - vibroizolace - 30.6.2026
A124: Leviat | B124: 46203 | C124: 46204 | D124: MONOKON s.r.o. | E124: BD Na Primoně | F124: ano | G124: izolační nosníky | I124: ="Poptávka TURTO - "&A124&" - "&IF(F124=data!$E$1,E124&" - ","")&G124&" - "&DAY(B124)&"."&MONTH(B124)&"."&YEAR(B124) -> Poptávka TURTO - Leviat - BD Na Primoně - izolační nosníky - 30.6.2026
A125: Peikko | B125: 46203 | C125: 46206 | D125: VALME s.r.o. | E125: Modernizace Nemocnice Frýdlant | F125: ne | G125: smyková výztuž | I125: ="Poptávka TURTO - "&A125&" - "&IF(F125=data!$E$1,E125&" - ","")&G125&" - "&DAY(B125)&"."&MONTH(B125)&"."&YEAR(B125) -> Poptávka TURTO - Peikko - smyková výztuž - 30.6.2026
A126: PohlCon | B126: 46203 | C126: 46205 | D126: VALME s.r.o. | E126: Modernizace Nemocnice Frýdlant | F126: ne | G126: smyková výztuž | I126: ="Poptávka TURTO - "&A126&" - "&IF(F126=data!$E$1,E126&" - ","")&G126&" - "&DAY(B126)&"."&MONTH(B126)&"."&YEAR(B126) -> Poptávka TURTO - PohlCon - smyková výztuž - 30.6.2026
A127: Nevoga | B127: 46203 | C127: 46204 | D127: PRAGIS a.s. | E127: Hydropolis | F127: ne | G127: vylamovací výztuž | I127: ="Poptávka TURTO - "&A127&" - "&IF(F127=data!$E$1,E127&" - ","")&G127&" - "&DAY(B127)&"."&MONTH(B127)&"."&YEAR(B127) -> Poptávka TURTO - Nevoga - vylamovací výztuž - 30.6.2026
A128: GeroTop | B128: 46203 | C128: 46203 | D128: V.D.O. Group s.r.o. | E128: Milan | F128: ne | G128: prostupy | I128: ="Poptávka TURTO - "&A128&" - "&IF(F128=data!$E$1,E128&" - ","")&G128&" - "&DAY(B128)&"."&MONTH(B128)&"."&YEAR(B128) -> Poptávka TURTO - GeroTop - prostupy - 30.6.2026
A129: Peikko | B129: 46202 | C129: 46205 | D129: SYNER, s.r.o. | E129: Víceúčelová budova Úvalská | F129: ano | G129: smyková výztuž | I129: ="Poptávka TURTO - "&A129&" - "&IF(F129=data!$E$1,E129&" - ","")&G129&" - "&DAY(B129)&"."&MONTH(B129)&"."&YEAR(B129) -> Poptávka TURTO - Peikko - Víceúčelová budova Úvalská - smyková výztuž - 29.6.2026
A130: Leviat | B130: 46202 | C130: 46202 | D130: STRABAG a.s. | E130: Vinohradská | F130: ano | G130: izolační nosníky | I130: ="Poptávka TURTO - "&A130&" - "&IF(F130=data!$E$1,E130&" - ","")&G130&" - "&DAY(B130)&"."&MONTH(B130)&"."&YEAR(B130) -> Poptávka TURTO - Leviat - Vinohradská - izolační nosníky - 29.6.2026
A131: Leviat | B131: 46202 | C131: 46202 | D131: BETONSERVIS s.r.o. | E131: Dolní stanice Hromovka 2 | F131: ano | G131: izolační nosníky | I131: ="Poptávka TURTO - "&A131&" - "&IF(F131=data!$E$1,E131&" - ","")&G131&" - "&DAY(B131)&"."&MONTH(B131)&"."&YEAR(B131) -> Poptávka TURTO - Leviat - Dolní stanice Hromovka 2 - izolační nosníky - 29.6.2026
A132: Leviat | B132: 46202 | C132: 46217 | D132: ABP HOLDING a.s. | E132: BIDFOOD Kralupy | F132: ano | G132: izolační nosníky | I132: ="Poptávka TURTO - "&A132&" - "&IF(F132=data!$E$1,E132&" - ","")&G132&" - "&DAY(B132)&"."&MONTH(B132)&"."&YEAR(B132) -> Poptávka TURTO - Leviat - BIDFOOD Kralupy - izolační nosníky - 29.6.2026
A133: PohlCon | B133: 46192 | C133: 46192 | D133: ARDEM STAVEBNÍ s.r.o. | E133: BD Zenklova | F133: ne | G133: smyková výztuž | I133: ="Poptávka TURTO - "&A133&" - "&IF(F133=data!$E$1,E133&" - ","")&G133&" - "&DAY(B133)&"."&MONTH(B133)&"."&YEAR(B133) -> Poptávka TURTO - PohlCon - smyková výztuž - 19.6.2026
A134: Peikko | B134: 46192 | C134: 46192 | D134: ARDEM STAVEBNÍ s.r.o. | E134: BD Zenklova | F134: ne | G134: smyková výztuž | I134: ="Poptávka TURTO - "&A134&" - "&IF(F134=data!$E$1,E134&" - ","")&G134&" - "&DAY(B134)&"."&MONTH(B134)&"."&YEAR(B134) -> Poptávka TURTO - Peikko - smyková výztuž - 19.6.2026
... A162: Leviat | B162: 46183 | C162: 46183 | D162: SYNER, s.r.o. | E162: Galerie Pardubice | F162: ne | G162: smykové trny | I162: ="Poptávka TURTO - "&A162&" - "&IF(F162=data!$E$1,E162&" - ","")&G162&" - "&DAY(B162)&"."&MONTH(B162)&"."&YEAR(B162) -> Poptávka TURTO - Leviat - smykové trny - 10.6.2026
A163: SIKA | B163: 46181 | C163: 46183 | D163: DoriJana | E163: DS Třebušín | F163: ne | G163: nátěr | H163: poptány vzorky znovu | I163: ="Poptávka TURTO - "&A163&" - "&IF(F163=data!$E$1,E163&" - ","")&G163&" - "&DAY(B163)&"."&MONTH(B163)&"."&YEAR(B163) -> Poptávka TURTO - SIKA - nátěr - 8.6.2026
A164: Leviat | B164: 46181 | C164: 46181 | D164: PREFA Roudná s. r. o. | E164: BD Zahrádky Branišovská | F164: ano | G164: izolační nosníky | I164: ="Poptávka TURTO - "&A164&" - "&IF(F164=data!$E$1,E164&" - ","")&G164&" - "&DAY(B164)&"."&MONTH(B164)&"."&YEAR(B164) -> Poptávka TURTO - Leviat - BD Zahrádky Branišovská - izolační nosníky - 8.6.2026
A165: PohlCon | B165: 46181 | C165: 46181 | D165: Petr Charvát | E165: Dolní Rokytná | F165: ne | G165: izolační nosníky | I165: ="Poptávka TURTO - "&A165&" - "&IF(F165=data!$E$1,E165&" - ","")&G165&" - "&DAY(B165)&"."&MONTH(B165)&"."&YEAR(B165) -> Poptávka TURTO - PohlCon - izolační nosníky - 8.6.2026
A166: Leviat | B166: 46181 | C166: 46181 | D166: Petr Charvát | E166: Dolní Rokytná | F166: ano | G166: izolační nosníky | I166: ="Poptávka TURTO - "&A166&" - "&IF(F166=data!$E$1,E166&" - ","")&G166&" - "&DAY(B166)&"."&MONTH(B166)&"."&YEAR(B166) -> Poptávka TURTO - Leviat - Dolní Rokytná - izolační nosníky - 8.6.2026
A167: Leviat | B167: 46180 | C167: 46181 | D167: VALENS, s.r.o. | E167: BD Boleslavova | F167: ano | G167: izolační nosníky | I167: ="Poptávka TURTO - "&A167&" - "&IF(F167=data!$E$1,E167&" - ","")&G167&" - "&DAY(B167)&"."&MONTH(B167)&"."&YEAR(B167) -> Poptávka TURTO - Leviat - BD Boleslavova - izolační nosníky - 7.6.2026
A168: Bettra | B168: 46178 | D168: NOVECON a.s. | E168: SO Zámeček Jenerálka | F168: ne | G168: prostupy | I168: ="Poptávka TURTO - "&A168&" - "&IF(F168=data!$E$1,E168&" - ","")&G168&" - "&DAY(B168)&"."&MONTH(B168)&"."&YEAR(B168) -> Poptávka TURTO - Bettra - prostupy - 5.6.2026
A169: GeroTop | B169: 46178 | C169: 46182 | D169: NOVECON a.s. | E169: SO Zámeček Jenerálka | F169: ano | G169: prostupy | H169: zrušeno | I169: ="Poptávka TURTO - "&A169&" - "&IF(F169=data!$E$1,E169&" - ","")&G169&" - "&DAY(B169)&"."&MONTH(B169)&"."&YEAR(B169) -> Poptávka TURTO - GeroTop - SO Zámeček Jenerálka - prostupy - 5.6.2026
A170: Leviat | B170: 46178 | C170: 46178 | D170: MAVI monolity s.r.o. | E170: BD U Zvonu | F170: ano | G170: izolační nosníky | I170: ="Poptávka TURTO - "&A170&" - "&IF(F170=data!$E$1,E170&" - ","")&G170&" - "&DAY(B170)&"."&MONTH(B170)&"."&YEAR(B170) -> Poptávka TURTO - Leviat - BD U Zvonu - izolační nosníky - 5.6.2026
A171: JFP TRADE | B171: 46178 | C171: 46181 | D171: ARDEM STAVEBNÍ s.r.o. | E171: Kolben Park III | F171: ano | G171: Sylodyn | I171: ="Poptávka TURTO - "&A171&" - "&IF(F171=data!$E$1,E171&" - ","")&G171&" - "&DAY(B171)&"."&MONTH(B171)&"."&YEAR(B171) -> Poptávka TURTO - JFP TRADE - Kolben Park III - Sylodyn - 5.6.2026
A172: Leviat | B172: 46178 | C172: 46178 | D172: BETONIT CZ s.r.o. | E172: SUPŠ Karlovy Vary | F172: ano | G172: izolační nosníky | I172: ="Poptávka TURTO - "&A172&" - "&IF(F172=data!$E$1,E172&" - ","")&G172&" - "&DAY(B172)&"."&MONTH(B172)&"."&YEAR(B172) -> Poptávka TURTO - Leviat - SUPŠ Karlovy Vary - izolační nosníky - 5.6.2026
A173: PohlCon | B173: 46178 | C173: 46181 | D173: STRABAG a.s. | E173: Vinohradská | F173: ne | G173: smyková výztuž | I173: ="Poptávka TURTO - "&A173&" - "&IF(F173=data!$E$1,E173&" - ","")&G173&" - "&DAY(B173)&"."&MONTH(B173)&"."&YEAR(B173) -> Poptávka TURTO - PohlCon - smyková výztuž - 5.6.2026
A174: Leviat | B174: 46178 | C174: 46178 | D174: SDMstav Praha s.r.o | E174: Rezidence Lochkov II | F174: ano | G174: izolační nosníky | I174: ="Poptávka TURTO - "&A174&" - "&IF(F174=data!$E$1,E174&" - ","")&G174&" - "&DAY(B174)&"."&MONTH(B174)&"."&YEAR(B174) -> Poptávka TURTO - Leviat - Rezidence Lochkov II - izolační nosníky - 5.6.2026
A175: Nevoga | B175: 46177 | C175: 46184 | D175: STRABAG a.s. | E175: Vinohradská | F175: ne | G175: monotub | H175: znovu poptáno | I175: ="Poptávka TURTO - "&A175&" - "&IF(F175=data!$E$1,E175&" - ","")&G175&" - "&DAY(B175)&"."&MONTH(B175)&"."&YEAR(B175) -> Poptávka TURTO - Nevoga - monotub - 4.6.2026
A176: Leviat | B176: 46177 | C176: 46178 | D176: PEVE Construct s.r.o. | E176: BD Starochodovská | F176: ano | G176: izolační nosníky | I176: ="Poptávka TURTO - "&A176&" - "&IF(F176=data!$E$1,E176&" - ","")&G176&" - "&DAY(B176)&"."&MONTH(B176)&"."&YEAR(B176) -> Poptávka TURTO - Leviat - BD Starochodovská - izolační nosníky - 4.6.2026
A177: PohlCon | B177: 46177 | C177: 46190 | D177: FERI, s.r.o. | E177: SO Zámeček Jenerálka | F177: ne | G177: vylamovací výztuž | H177: 9/6 urgováno | I177: ="Poptávka TURTO - "&A177&" - "&IF(F177=data!$E$1,E177&" - ","")&G177&" - "&DAY(B177)&"."&MONTH(B177)&"."&YEAR(B177) -> Poptávka TURTO - PohlCon - vylamovací výztuž - 4.6.2026
...

Sheet MIVO
A1: Poptáno | B1: Obdrženo | C1: Klient | D1: Akce | E1: Uvedená akce | F1: Poptáváno | G1: poznámka | H1: Předmět mailu
H2: ="Optimalizace - "&C2&" - "&IF(E2=data!$E$2,"",D2&" - ")&F2&" - "&DAY(A2)&"."&MONTH(A2)&"."&YEAR(A2) -> Optimalizace - - - - 0.1.1900
A3: 46248 | C3: PORR a.s. | D3: BD Zelený Kamýk | E3: ano | F3: izolační nosníky | H3: Návrh izolačních nosníků - PORR - BD Zelený Kamýk
A4: 46238 | C4: Hinton, a.s. | D4: Meander Kbely | E4: ano | F4: izolační nosníky | H4: Návrh izolačních nosníků - HINTON - Meander Kbely
A5: 46233 | B5: 46233 | C5: Hinton, a.s. | D5: Za Valem D1-D3 | E5: ano | F5: izolační nosníky | H5: ="Optimalizace - "&C5&" - "&IF(E5=data!$E$2,"",D5&" - ")&F5&" - "&DAY(A5)&"."&MONTH(A5)&"."&YEAR(A5) -> Optimalizace - Hinton, a.s. - Za Valem D1-D3 - izolační nosníky - 30.7.2026
A6: 46227 | C6: FERI, s.r.o. | D6: Rohan City Block B2 | E6: ano | F6: izolační nosníky | H6: Návrh izolačních nosníků - FERI - Nový Rohan sekce A Blok B2
A7: 46206 | B7: 46206 | C7: PORR a.s. | D7: OS Nad Čimickým Údolím | E7: ano | F7: izolační nosníky
A8: 46204 | B8: 46213 | C8: PEVE Construct s.r.o. | D8: BD Starochodovská | E8: ano | F8: izolační nosníky | H8: Návrh izolačních nosníků - PEVE - BD Starochodovská
A9: 46204 | B9: 46204 | C9: BBP monolit s.r.o. | D9: BD Křimice | E9: ano | F9: izolační nosníky | H9: Návrh izolačních nosníků - BBP - BD Křimice
A10: 46196 | C10: Stavební společnost SIPA s.r.o. | D10: BD Plzeň | E10: ano | H10: FW: ISOKORBY BD Plzeň
A11: 46181 | C11: Winning PS - Pamstav s.r.o. | D11: Kolben Park Objekt B | E11: ano | H11: Kolben Park etapa III - Objekt B
A12: 46178 | B12: 46204 | C12: Gardenline s.r.o. | D12: BD Březinova | H12: Gardenline - BD Březinova - XYPEX
A13: 46177 | B13: 46178 | C13: MAVI monolity s.r.o. | D13: BD U Zvonu | H13: Návrh izolačních nosníků - MAVI - BD U Zvonu
A14: 46170 | B14: 46191 | C14: Hinton, a.s. | D14: Pitkovický Dvůr | E14: ano | F14: izolační nosníky | H14: Návrh izolačních nosníků - Hinton - Pitkovický Dvůr
A15: 46165 | B15: 46167 | C15: JS Monolity, s.r.o. | D15: ATB Ruzyně | E15: ano | H15: Vlepení výztuže - FW: Foto Ruzyně
A16: 46163 | C16: MAKEDOSTAV, s.r.o. | D16: Dům Vršovice | E16: ano | F16: izolační nosníky | H16: Nosníky OCEL-BETON - Dům Vršovice - izolační nosníky - 21.5.2026
A17: 46154 | C17: Budžak Building s.r.o. | D17: BD Kbely | E17: ano | F17: izolační nosníky | H17: ="Optimalizace - "&C17&" - "&IF(E17=data!$E$2,"",D17&" - ")&F17&" - "&DAY(A17)&"."&MONTH(A17)&"."&YEAR(A17) -> Optimalizace - Budžak Building s.r.o. - BD Kbely - izolační nosníky - 12.5.2026
A18: 46153 | B18: 46191 | C18: GriToN CZ s.r.o. | D18: Petynka | H18: Návrh izolačních nosníků - GRITON - Petynka
A19: 46147 | D19: BD Nový Zeleneč | H19: Podklady - Nový Zeleneč
A20: 46146 | B20: 46146 | C20: SYNER, s.r.o. | D20: Víceúčelová budova Úvalská | E20: ano | F20: izolační nosníky | H20: Optimalizace - Syner - Víceúčelová budova Úvalská - 4.5.2026
A21: 46132 | B21: 46154 | C21: PP 53, a.s. | D21: BD U Pivovaru II - Benešov | E21: ano | F21: izolační nosníky | H21: Návrh izolačních nosníků - PP53 - BD U Pivovaru II - Benešov - 20.4.2026
A22: 46132 | B22: 46157 | C22: PP 53, a.s. | D22: BD Parmská | E22: ano | F22: izolační nosníky | H22: Podklady - PP53 BD Parmská
A23: 46110 | B23: 46113 | C23: PP 53, a.s. | D23: BD Parmská | E23: ano | F23: izolační nosníky | H23: ="Optimalizace - "&C23&" - "&IF(E23=data!$E$2,"",D23&" - ")&F23&" - "&DAY(A23)&"."&MONTH(A23)&"."&YEAR(A23) -> Optimalizace - PP 53, a.s. - BD Parmská - izolační nosníky - 29.3.2026
A24: 46100 | B24: 46102 | C24: PP 53, a.s. | D24: Kaskády Barrandov | E24: ano | F24: izolační nosníky | H24: ="Optimalizace - "&C24&" - "&IF(E24=data!$E$2,"",D24&" - ")&F24&" - "&DAY(A24)&"."&MONTH(A24)&"."&YEAR(A24) -> Optimalizace - PP 53, a.s. - Kaskády Barrandov - izolační nosníky - 19.3.2026
A25: 46097 | B25: 46103 | C25: C&S MONOLITIA s.r.o. | D25: MOSAIQ Beroun | E25: ano | F25: izolační nosníky | H25: ="Optimalizace - "&C25&" - "&IF(E25=data!$E$2,"",D25&" - ")&F25&" - "&DAY(A25)&"."&MONTH(A25)&"."&YEAR(A25) -> Optimalizace - C&S MONOLITIA s.r.o. - MOSAIQ Beroun - izolační nosníky - 16.3.2026
C26: BETONSERVIS s.r.o. | D26: BD Hořice | E26: ano | F26: izolační nosníky | H26: ="Optimalizace - "&C26&" - "&IF(E26=data!$E$2,"",D26&" - ")&F26&" - "&DAY(A26)&"."&MONTH(A26)&"."&YEAR(A26) -> Optimalizace - BETONSERVIS s.r.o. - BD Hořice - izolační nosníky - 0.1.1900
A27: 46091 | B27: 46092 | C27: MAVI monolity s.r.o. | D27: Papírna N1 | H27: ="izolační nosníky - "&C27&" - "&IF(E27=data!$E$2,"",D27&" - ")&F27&DAY(A27)&"."&MONTH(A27)&"."&YEAR(A27) -> izolační nosníky - MAVI monolity s.r.o. - Papírna N1 - 10.3.2026
A28: 46091 | B28: 46092 | C28: PORR a.s. | D28: Hodkovičky | H28: ="Vibroizolace - "&C28&" - "&IF(E28=data!$E$2,"",D28&" - ")&F28&DAY(A28)&"."&MONTH(A28)&"."&YEAR(A28) -> Vibroizolace - PORR a.s. - Hodkovičky - 10.3.2026
A29: 46091 | B29: 46091 | C29: PRAGIS a.s. | D29: DUO Living | E29: ano | H29: ="Brandenburger S4000 - "&C29&" - "&IF(E29=data!$E$2,"",D29&" - ")&F29&DAY(A29)&"."&MONTH(A29)&"."&YEAR(A29) -> Brandenburger S4000 - PRAGIS a.s. - DUO Living - 10.3.2026
A30: 46110 | B30: 46126 | C30: MAVI monolity s.r.o. | D30: BD 11 Máchovna
A31: 46087 | B31: 46087 | C31: Prefab Factory a.s. | G31: viz Honza | H31: Záměna za Sylomer - prefa koupelny - 6.3.2026
A32: 46110 | C32: VALENS, s.r.o. | D32: Polyfunkční dům Prcek - Vyškov | G32: zrušeno
A33: 46087 | B33: 46113 | C33: PHARMOS, a.s. | D33: Apartmány Odra | E33: ano | F33: izolační nosníky | H33: ="Optimalizace - "&C33&" - "&IF(E33=data!$E$2,"",D33&" - ")&F33&" - "&DAY(A33)&"."&MONTH(A33)&"."&YEAR(A33) -> Optimalizace - PHARMOS, a.s. - Apartmány Odra - izolační nosníky - 6.3.2026
A34: 46084 | D34: FN Plzeň - pavilon chirurgických oborů | E34: ano | G34: info do budoucna | H34: Info - FN Plzeň - pavilon chirurgických oborů
A35: 46084 | B35: 46084 | C35: JAPS TEN s.r.o. | D35: RD Vonoklasy | E35: ano | F35: izolační nosníky | H35: ="Optimalizace - "&C35&" - "&IF(E35=data!$E$2,"",D35&" - ")&F35&" - "&DAY(A35)&"."&MONTH(A35)&"."&YEAR(A35) -> Optimalizace - JAPS TEN s.r.o. - RD Vonoklasy - izolační nosníky - 3.3.2026
A36: 46083 | B36: 46089 | C36: STRABAG a.s. | D36: Campus Česká Spořitelna | E36: ano | F36: vibroizolace | H36: ="Kladecí schéma - "&C36&" - "&IF(E36=data!$E$2,"",D36&" - ")&F36&" - "&DAY(A36)&"."&MONTH(A36)&"."&YEAR(A36) -> Kladecí schéma - STRABAG a.s. - Campus Česká Spořitelna - vibroizolace - 2.3.2026
A37: 46083 | B37: 46090 | C37: PORR a.s. | D37: BD Záběhlická | E37: ano | F37: izolační nosníky | H37: ="Optimalizace - "&C37&" - "&IF(E37=data!$E$2,"",D37&" - ")&F37&" - "&DAY(A37)&"."&MONTH(A37)&"."&YEAR(A37) -> Optimalizace - PORR a.s. - BD Záběhlická - izolační nosníky - 2.3.2026
A38: 46078 | B38: 46122 | C38: ELRAIL s.r.o. | D38: BD Rokycany | E38: ano | F38: izolační nosníky | H38: ="Optimalizace - "&C38&" - "&IF(E38=data!$E$2,"",D38&" - ")&F38&" - "&DAY(A38)&"."&MONTH(A38)&"."&YEAR(A38) -> Optimalizace - ELRAIL s.r.o. - BD Rokycany - izolační nosníky - 25.2.2026
D39: Medový újezd | H39: ="Optimalizace - "&C39&" - "&IF(E39=data!$E$2,"",D39&" - ")&F39&" - "&DAY(A39)&"."&MONTH(A39)&"."&YEAR(A39) -> Optimalizace - - Medový újezd - - 0.1.1900
A40: 46075 | C40: VALME s.r.o. | D40: OS Podlesí | E40: ano | F40: izolační nosníky | H40: ="Optimalizace - "&C40&" - "&IF(E40=data!$E$2,"",D40&" - ")&F40&" - "&DAY(A40)&"."&MONTH(A40)&"."&YEAR(A40) -> Optimalizace - VALME s.r.o. - OS Podlesí - izolační nosníky - 22.2.2026
A41: 46075 | C41: TURTO s.r.o. | D41: HIT - statické tabulky | E41: ne | H41: Únosnosti Leviat - HIT MVX
C42: FERI, s.r.o.

Sheet Akce
A9: Anglické nábřeží
A10: Apartmány Odra
A11: Apartmány Rokytná
A12: BD Čimická
A13: BD Jaroměř
A14: BD Jezarky
A15: BD Odkolek
A16: BD Odkolek
A17: BD Petrská 18
A18: BD Starochodovská
A19: BD Třešňová
A20: BD Zelený Kamýk
... A297: BD Košinka

Sheet data
A1: ABATO SERVIS s.r.o. | B1: Jan Mayer | C1: připraveno | D1: Leviat | E1: ano | F1: izolační nosníky
A2: ABP a.s. Praha | B2: Jiří Cír | C2: zpracováno | D2: PohlCon | E2: ne | F2: smykové trny
A3: ABP HOLDING a.s. | B3: Milan Soukup | C3: zrušeno | D3: MaxFrank | F3: smyková výztuž
A4: AB systém CZ s.r.o. | B4: Vít Hrdlička | C4: jiný | D4: GeroTop | F4: lenton spojky
A5: ACARA PRAHA,s.r.o. | B5: Michal Voplakal | D5: Peikko | F5: prostupy
A6: ACISTAV, s.r.o. | D6: Pro-Doma | F6: GR desky
A7: A.D.S. Rokycany s.r.o. | D7: Nevoga | F7: vylamovací výztuž
A8: AED projekt | D8: Pragoelast | F8: mezivýplň
A9: AF STAV Group s.r.o. | D9: Michal Voplakal | F9: ISOLINK
A10: Akční tisk, s.r.o. | D10: GMYS | F10: Sylomer
A11: AKORA s.r.o. | D11: JFP TRADE | F11: vibroizolace
A12: AKTIVITA plus s.r.o. | D12: MIVO | F12: kluzná ložiska
A13: AKT STAV s.r.o. | D13: EXPAN | F13: Halfen HKW
A14: ALBANESE | D14: DIMER | F14: dilatační profil
A15: ALFA MONOLIT s.r.o. | D15: Biguma | F15: Halfen HTF
A16: ALGON, a.s. | D16: MEA | F16: Brandenburger S4000
A17: Allianz pojišťovna, a.s. | D17: PERI | F17: SINTON X
... A23: Alza.cz a.s. | D23: SANAX | F23: těsnicí vložka
A24: Amazing Tours, a.s. | F24: kotevní lišty
A25: AMO, spol. s r.o. | F25: Halfen Deha
A26: Andres a Vild, spol. s r.o. | F26: PVC pásy
A27: ANP - Systems GmbH | F27: kotevní body
A28: APB - PLZEŇ a.s. | F28: spojky výztuže
A29: ARDEM STAVEBNÍ s.r.o. | F29: vlnová kotva
A30: Arch Construct s.r.o. | F30: BENTOMAT
A31: Archetiko, s.r.o. | F31: MIGUTAN
A32: architekti NAHRANĚ s.r.o. | F32: HTA
A33: ARLEPA Projekt s.r.o. | F33: Carbo lamela
A34: ARMONTIS BeSt s.r.o. | F34: Sika Emako
A35: ARMOVNA Otovice s.r.o. | F35: plech ABS
... A47: AVE CZ odpadové hospodářství s.r.o. | F47: Sikaflex Construction+
A48: A V stav, spol. s r.o.
A49: A-X s.r.o.
A50: Azivex s.r.o.
A51: az-reptec GbR
A52: A2K-STAV s.r.o.
A53: BAGOSTAV s.r.o.
A54: BAKNER s.r.o.
A55: BAK stavební společnost, a.s.
A56: BAM Group s.r.o.
A57: BAUFERA s.r.o.
A58: BAU-STAV a.s.
A59: BAZISSTAV group s.r.o.
... A825: HRABÁNEK s.r.o.
